[["Map",1,2,9,10],"meta::meta",["Map",3,4,5,6,7,8],"astro-version","5.18.1","content-config-digest","f586036227d7e172","astro-config-digest","{\"root\":{},\"srcDir\":{},\"publicDir\":{},\"outDir\":{},\"cacheDir\":{},\"site\":\"https://your-github-username.github.io\",\"compressHTML\":true,\"base\":\"/academic-homepage\",\"trailingSlash\":\"ignore\",\"output\":\"static\",\"scopedStyleStrategy\":\"attribute\",\"build\":{\"format\":\"directory\",\"client\":{},\"server\":{},\"assets\":\"_astro\",\"serverEntry\":\"entry.mjs\",\"redirects\":true,\"inlineStylesheets\":\"auto\",\"concurrency\":1},\"server\":{\"open\":false,\"host\":false,\"port\":4321,\"streaming\":true,\"allowedHosts\":[]},\"redirects\":{},\"image\":{\"endpoint\":{\"route\":\"/_image\"},\"service\":{\"entrypoint\":\"astro/assets/services/sharp\",\"config\":{}},\"domains\":[],\"remotePatterns\":[],\"responsiveStyles\":false},\"devToolbar\":{\"enabled\":true},\"markdown\":{\"syntaxHighlight\":{\"type\":\"shiki\",\"excludeLangs\":[\"math\"]},\"shikiConfig\":{\"langs\":[],\"langAlias\":{},\"theme\":\"github-dark\",\"themes\":{},\"wrap\":false,\"transformers\":[]},\"remarkPlugins\":[],\"rehypePlugins\":[],\"remarkRehype\":{},\"gfm\":true,\"smartypants\":true},\"security\":{\"checkOrigin\":true,\"allowedDomains\":[],\"actionBodySizeLimit\":1048576},\"env\":{\"schema\":{},\"validateSecrets\":false},\"experimental\":{\"clientPrerender\":false,\"contentIntellisense\":false,\"headingIdCompat\":false,\"preserveScriptOrder\":false,\"liveContentCollections\":false,\"csp\":false,\"staticImportMetaEnv\":false,\"chromeDevtoolsWorkspace\":false,\"failOnPrerenderConflict\":false,\"svgo\":false},\"legacy\":{\"collections\":false}}","papers",["Map",11,12,46,47],"vehiclemae",{"id":11,"data":13,"filePath":32,"digest":33,"rendered":34,"legacyId":45},{"title":14,"authors":15,"venue":19,"venueType":20,"venueLevel":21,"acceptedDate":22,"fieldTags":23,"levelTags":27,"image":28,"paperUrl":29,"summary":30,"abstract":31},"VehicleMAE: Masked Autoencoding for Robust Vehicle Re-Identification",[16,17,18],"Dong Wang","Author D","Author E","IEEE Transactions on Intelligent Transportation Systems","Journal","SCI-Q1","2025-11-18",[24,25,26],"Vehicle Re-ID","Autonomous Driving","Multimodal Learning",[21,20],"/images/papers/vehiclemae.png","https://example.com/paper","A masked autoencoding approach for learning robust vehicle representations under challenging visual conditions.","This paper presents VehicleMAE, a masked autoencoding framework designed for robust vehicle re-identification. By reconstructing masked visual evidence and aligning discriminative identity cues, the method improves representation quality under occlusion, viewpoint variation, and illumination changes.","src/content/papers/vehiclemae.md","45f18643e2cf098a",{"html":35,"metadata":36},"",{"headings":37,"localImagePaths":38,"remoteImagePaths":39,"frontmatter":40,"imagePaths":44},[],[],[],{"slug":11,"title":14,"authors":41,"venue":19,"venueType":20,"venueLevel":21,"acceptedDate":22,"fieldTags":42,"levelTags":43,"image":28,"paperUrl":29,"summary":30,"abstract":31},[16,17,18],[24,25,26],[21,20],[],"vehiclemae.md","specbridge",{"id":46,"data":48,"filePath":65,"digest":66,"rendered":67,"legacyId":77},{"title":49,"authors":50,"venue":53,"venueType":54,"venueLevel":55,"acceptedDate":56,"fieldTags":57,"levelTags":60,"image":62,"paperUrl":35,"summary":63,"abstract":64},"SpecBridge: Spectral Graph Bridging for 3D-2D-Text Pre-training",[16,51,52],"Author B","Author C","IJCAI-ECAI 2026","Conference","CCF-B","2026-04-29",[58,59],"3D Vision","Vision-Language Learning",[55,61],"International Conference","/images/papers/specbridge.png","A 3D-2D-Text pre-training framework for open-vocabulary 3D understanding.","This paper introduces a 3D-2D-Text pre-training framework for open-vocabulary 3D understanding. The method bridges 3D, 2D, and text modalities through structural and semantic alignment.","src/content/papers/specbridge.md","e83061d1b6641744",{"html":35,"metadata":68},{"headings":69,"localImagePaths":70,"remoteImagePaths":71,"frontmatter":72,"imagePaths":76},[],[],[],{"slug":46,"title":49,"authors":73,"venue":53,"venueType":54,"venueLevel":55,"acceptedDate":56,"fieldTags":74,"levelTags":75,"image":62,"paperUrl":35,"summary":63,"abstract":64},[16,51,52],[58,59],[55,61],[],"specbridge.md"]